Metadata-Version: 2.1
Name: sqlite3py
Version: 1.0.2
Summary: Module sqlite3py provides you smart requests for sqlite database by Xpos587
Home-page: https://github.com/Xpos587/Sqlite3py
Download-URL: https://github.com/Xpos587/Sqlite3py/tree/master/releases/v1.0.2.zip
Author: Xpos587
Author-email: x30827pos@gmail.com
License: MIT License, Copyright (c) 2022 Xpos587, see LICENSE file.
Requires: sqlite3
License-File: LICENSE
